{"graph": [], "multigraph": false, "nodes": [{"page": "144", "pos_on_page": "41", "id": "tsi\u0301i\u0301ho", "data_source": "leach1969"}, {"page": "113", "pos_on_page": "5", "id": "ti\u0335\u0301fai", "data_source": "walton1997"}, {"id": "boa"}, {"id": "rojo"}, {"page": "270", "pos_on_page": "25", "id": "tu\u0301jpa\u0301h", "data_source": "thiesen1998"}, {"page": "270", "pos_on_page": "25", "id": "tu\u0301jpa\u0301", "data_source": "thiesen1998"}, {"id": "bmr"}, {"page": "270", "pos_on_page": "30", "id": "tu\u0301jpan\u0303e", "data_source": "thiesen1998"}, {"id": "oca"}], "directed": false, "links": [{"source": 0, "target": 8}, {"source": 1, "target": 6}, {"source": 2, "target": 5}, {"source": 2, "target": 7}, {"source": 2, "target": 3}, {"source": 2, "target": 4}, {"source": 3, "target": 8}, {"source": 3, "target": 6}]}