{"graph": [], "multigraph": false, "nodes": [{"id": "camino"}, {"page": "190", "pos_on_page": "12", "id": "nai\u0335so", "data_source": "burtch1983"}, {"page": "871", "pos_on_page": "20", "id": " naai\u0335zo", "data_source": "preuss1994"}, {"id": "oca"}, {"page": "871", "pos_on_page": "20", "id": "naai\u0335zuei\u0335", "data_source": "preuss1994"}, {"page": "855", "pos_on_page": "18", "id": "kaidaja", "data_source": "preuss1994"}, {"id": "huu"}, {"id": "bmr"}, {"page": "160", "pos_on_page": "17", "id": "juva\u0301n\u0303e", "data_source": "thiesen1998"}, {"page": "855", "pos_on_page": "18", "id": " kaidaka", "data_source": "preuss1994"}, {"page": "297", "pos_on_page": "6", "id": "ulle\u0301ji\u0335\u0301jto", "data_source": "thiesen1998"}, {"page": "124", "pos_on_page": "10", "id": "hto", "data_source": "leach1969"}, {"page": "871", "pos_on_page": "20", "id": "naai\u0335", "data_source": "preuss1994"}, {"id": "boa"}, {"page": "160", "pos_on_page": "17", "id": "juu\u0301va", "data_source": "thiesen1998"}, {"page": "24", "pos_on_page": "20", "id": "io", "data_source": "minor1971"}, {"page": "77", "pos_on_page": "18", "id": "ji\u0335\u0301i\u0335\u0301hai", "data_source": "walton1997"}, {"page": "124", "pos_on_page": "10", "id": "jo", "data_source": "leach1969"}, {"page": "190", "pos_on_page": "12", "id": "nai\u0335", "data_source": "burtch1983"}, {"page": "27", "pos_on_page": "17", "id": "jai\u0301lledi\u0335", "data_source": "minor1971"}, {"page": "124", "pos_on_page": "8", "id": "naajon", "data_source": "leach1969"}, {"page": "855", "pos_on_page": "18", "id": "kaidade", "data_source": "preuss1994"}], "directed": false, "links": [{"source": 0, "target": 11}, {"source": 0, "target": 13}, {"source": 0, "target": 6}, {"source": 0, "target": 3}, {"source": 0, "target": 7}, {"source": 1, "target": 6}, {"source": 2, "target": 6}, {"source": 3, "target": 11}, {"source": 3, "target": 20}, {"source": 3, "target": 17}, {"source": 4, "target": 6}, {"source": 5, "target": 6}, {"source": 6, "target": 12}, {"source": 6, "target": 9}, {"source": 6, "target": 18}, {"source": 6, "target": 21}, {"source": 7, "target": 16}, {"source": 8, "target": 13}, {"source": 10, "target": 13}, {"source": 11, "target": 19}, {"source": 11, "target": 15}, {"source": 13, "target": 14}]}